{
  "foodData": [
    { "id": 1,
      "width": 200,
      "height": 200,
      "name": "Stir-Fry Chicken",
      "description": "Delicious stir-fry chicken with peppers and onions in a sweet onion sauce.",
      "category": "Entrees"
    },
    { "id": 2,
      "width": 200,
      "height": 200,
      "name": "Beef Salad",
      "description": "Marinated beef atop a fresh bed of lettuce with onions and tomatoes.",
      "category": "Entrees"
    },
    { "id": 3,
      "width": 200,
      "height": 200,
      "name": "Pizza Strips",
      "description": "Pizza strips with our homemade tomato dipping sauce.",
      "category": "Appetizers"
    },
    { "id": 4,
      "width": 200,
      "height": 200,
      "name": "Mini Sushi",
      "description": "A small sushi treat including a California roll, tuna, and salmon.",
      "category": "Appetizers"
    },
    { "id": 5,
      "width": 200,
      "height": 200,
      "name": "Veggie Delight",
      "description": "Various fresh veggies for the veggie lover.",
      "category": "Appetizers"
    },
    { "id": 6,
      "width": 200,
      "height": 200,
      "name": "Roasted Vegetables",
      "description": "A medley of roasted vegetables in our special garlic sauce.",
      "category": "Entrees"
    },
    { "id": 7,
      "width": 200,
      "height": 200,
      "name": "Bread Rolls",
      "description": "Order an extra helping of our homemade bread rolls.",
      "category": "Bread"
    },
    { "id": 8,
      "width": 200,
      "height": 200,
      "name": "Sushi Special (Vegetarian)",
      "description": "A special medley of vegetarian sushi rolls.",
      "category": "Entrees"
    },
    { "id": 9,
      "width": 200,
      "height": 200,
      "name": "All-Beef Cheeseburger",
      "description": "A hearty serving of beef with onion, lettuce, and tomato on a homemade bun.",
      "category": "Entrees"
    }
  ]
}